cellsnap/__init__.py
cellsnap/cellsnap.py
cellsnap/datasets.py
cellsnap/graph.py
cellsnap/main.py
cellsnap/models.py
cellsnap/preprocessing.py
cellsnap/utils.py
cellsnap-0.1.0.dist-info/LICENSE
cellsnap-0.1.0.dist-info/METADATA
cellsnap-0.1.0.dist-info/WHEEL
cellsnap-0.1.0.dist-info/top_level.txt
cellsnap-0.1.0.dist-info/RECORD
