Metadata-Version: 2.1
Name: cellsnap
Version: 0.1.0
Summary: A package for enhancing single-cell population delineation by integrating cross-domain information.
Home-page: https://github.com/sggao/cellsnap
Author: Sheng Gao, Bokai Zhu
Author-email: gaosheng0321@gmail.com, zhubokai@mit.edu
Project-URL: Bug Tracker, https://github.com/sggao/cellsnap/issues
Classifier: Programming Language :: Python :: 3
Classifier: License :: OSI Approved :: MIT License
Classifier: Operating System :: OS Independent
Requires-Python: >=3.8
License-File: LICENSE
Requires-Dist: anndata>=0.10.6
Requires-Dist: leidenalg>=0.9.1
Requires-Dist: matplotlib>=3.7.1
Requires-Dist: numpy>=1.26.0
Requires-Dist: pandas>=2.0.0
Requires-Dist: python-igraph>=0.11.4
Requires-Dist: scanpy>=1.10.0
Requires-Dist: scikit-image>=0.21.0
Requires-Dist: scikit-learn>=1.2.2
Requires-Dist: scipy>=1.10.0
Requires-Dist: torch>=1.12.0
Requires-Dist: torch-geometric>=2.3.0
Requires-Dist: torchvision>=0.13.1
Requires-Dist: tqdm>=4.64.1
